unixevents/__init__.py
unixevents/unixevents.py
unixevents-0.0.2.dist-info/METADATA
unixevents-0.0.2.dist-info/WHEEL
unixevents-0.0.2.dist-info/RECORD
