Metadata-Version: 2.4
Name: unixevents
Version: 0.0.2
Summary: Unixevents is a lightweight inter-process communication (IPC) library available in both JavaScript (Node.js) and Python. It enables real-time, event-driven communication across processes or applications — regardless of the language they are written in.
Project-URL: Homepage, https://github.com/rohsins/unixevents_py
Project-URL: Issues, https://github.com/rohsins/unixevents_py/issues
Author-email: Rohit Singh <rohsins@gmail.com>
License-Expression: MIT
Keywords: communication,events,ipc,unixevents
Classifier: Operating System :: OS Independent
Classifier: Programming Language :: Python :: 3
Requires-Python: >=3.9
